flet_mobile_preview/__init__.py
flet_mobile_preview/iPhone.py
flet_mobile_preview/assets/icon.png
flet_mobile_preview/assets/fonts/sf.otf
flet_mobile_preview-1.0.4.dist-info/METADATA
flet_mobile_preview-1.0.4.dist-info/WHEEL
flet_mobile_preview-1.0.4.dist-info/top_level.txt
flet_mobile_preview-1.0.4.dist-info/RECORD
