Metadata-Version: 2.1
Name: flet_mobile_preview
Version: 1.0.4
Summary: A simple phone preview for Flet applications
Home-page: https://github.com/Victoire243/flet-phone-preview.git
Author: Victoire Kitenge
Author-email: yumakitenge243@gmail.com
Classifier: Programming Language :: Python :: 3
Classifier: License :: OSI Approved :: MIT License
Classifier: Operating System :: OS Independent
Requires-Python: >=3.10
Requires-Dist: flet
